animl2/__init__.py
animl2/core/__init__.py
animl2/core/annotations.py
animl2/core/base.py
animl2/core/fields.py
animl2/models/__init__.py
animl2/models/author.py
animl2/models/base.py
animl2/models/category.py
animl2/models/common.py
animl2/models/data_type.py
animl2/models/device.py
animl2/models/doc.py
animl2/models/experiment.py
animl2/models/infrastructure.py
animl2/models/method.py
animl2/models/parameter.py
animl2/models/sample.py
animl2/models/series.py
animl2/models/software.py
animl2/models/tags.py
animl2/models/technique.py
animl2/models/unit.py
animl2/models/valuesets.py
animl2/utils/regex.py
animl2-0.1.2.dist-info/LICENSE
animl2-0.1.2.dist-info/METADATA
animl2-0.1.2.dist-info/WHEEL
animl2-0.1.2.dist-info/top_level.txt
animl2-0.1.2.dist-info/RECORD
