Metadata-Version: 2.1
Name: animl2
Version: 0.1.2
Summary: Python library for working with AnIML files
Author-email: Erik Trygg <etrg@novonordisk.com>
Project-URL: Homepage, https://github.com/Firefly78/py-animl
Project-URL: Repository, https://github.com/Firefly78/py-animl
Project-URL: Bug Tracker, https://github.com/Firefly78/py-animl/issues
Project-URL: AnIML: Home, https://animl.org
Classifier: Development Status :: 3 - Alpha
Classifier: Programming Language :: Python :: 3
Classifier: License :: OSI Approved :: MIT License
Classifier: Operating System :: OS Independent
Requires-Python: >=3.9
License-File: LICENSE
Provides-Extra: dev
Requires-Dist: black ==24.4.1 ; extra == 'dev'
Requires-Dist: bumpver ; extra == 'dev'
Requires-Dist: flake8 ==7.0.0 ; extra == 'dev'
Requires-Dist: isort ==5.13.2 ; extra == 'dev'
Requires-Dist: pytest ; extra == 'dev'
